solidipes_astro_plugin/__init__.py
solidipes_astro_plugin/loaders/fits.py
solidipes_astro_plugin/viewers/aladin_lite.py
solidipes_astro_plugin/viewers/astrovisjs.py
solidipes_astro_plugin-0.0.2.dist-info/METADATA
solidipes_astro_plugin-0.0.2.dist-info/WHEEL
solidipes_astro_plugin-0.0.2.dist-info/entry_points.txt
solidipes_astro_plugin-0.0.2.dist-info/licenses/LICENSE
solidipes_astro_plugin-0.0.2.dist-info/RECORD
