Metadata-Version: 2.4
Name: solidipes-astro-plugin
Version: 0.0.2
Summary: Plugin for Solidipes with astrophysics components
License: GPL-3.0-or-later
License-File: LICENSE
Author: Son Pham-Ba
Author-email: son.phamba@epfl.ch
Requires-Python: >=3.9.12,<3.13
Classifier: License :: OSI Approved :: GNU General Public License v3 or later (GPLv3+)
Classifier: Programming Language :: Python :: 3
Classifier: Programming Language :: Python :: 3.10
Classifier: Programming Language :: Python :: 3.11
Classifier: Programming Language :: Python :: 3.12
Provides-Extra: dev
Provides-Extra: test
Requires-Dist: build (>=1.0.3,<2.0.0) ; extra == "dev"
Requires-Dist: pre-commit (>=3.0.4,<4.0.0) ; extra == "dev"
Requires-Dist: pytest (>=8.1.1,<9.0.0) ; extra == "dev" or extra == "test"
Requires-Dist: pytest-cov (>=5.0.0,<6.0.0) ; extra == "dev" or extra == "test"
Requires-Dist: solidipes (>=0.0.0)
